amherst/__init__.py
amherst/actions/__init__.py
amherst/actions/convert_tracking.py
amherst/actions/emailer.py
amherst/actions/invoice_number.py
amherst/actions/invoicer/inv.py
amherst/actions/one_shots.py
amherst/actions/payment_status.py
amherst/actions/shipment_tracker.py
amherst/actions/stockcheck.py
amherst/app.py
amherst/back/__init__.py
amherst/back/backend_pycommence.py
amherst/back/backend_search_paginate.py
amherst/back/callbacks.py
amherst/back/routes_html.py
amherst/back/routes_json.py
amherst/back/ship_routes.py
amherst/cli.py
amherst/cli2.py
amherst/config.py
amherst/models/__init__.py
amherst/models/amherst_models.py
amherst/models/cmc_update.py
amherst/models/commence_adaptors.py
amherst/models/filters.py
amherst/models/maps.py
amherst/models/meta.py
amherst/models/order_ent.py
amherst/models/order_ent25.py
amherst/models/shipment.py
amherst/office_am/__init__.py
amherst/office_am/assets.py
amherst/office_am/commence vbs/functional/hire_funcs.vbs
amherst/office_am/commence vbs/functional/hire_functional.VBS
amherst/office_am/commence vbs/functional/paul_funcs_24.vbs
amherst/office_am/commence vbs/giles_customer_checkout#.VBS
amherst/office_am/commence vbs/paul_hire.VBS
amherst/office_am/commence vbs/paul_hire_checkout.VBS
amherst/office_am/commence vbs/paul_sale_detail_24.VBS
amherst/office_am/commence vbs/repair_lines.vbs
amherst/office_am/commence vbs/repairs2.vbs
amherst/office_am/commence vbs/repairs_checkout.VBS
amherst/office_am/dflt.py
amherst/office_am/exceptions.py
amherst/office_am/main.py
amherst/office_am/merge_docs/__init__.py
amherst/office_am/merge_docs/box_label.py
amherst/office_am/order/__init__.py
amherst/office_am/order/invoice.py
amherst/office_am/order/order_ent.py
amherst/office_am/order/transact.py
amherst/office_am/static/__init__.py
amherst/office_am/static/backup/box_temp.doc
amherst/office_am/static/backup/box_tmplt.docx
amherst/office_am/static/backup/commence_invoice_template.doc
amherst-0.4.2.dist-info/WHEEL
amherst-0.4.2.dist-info/entry_points.txt
amherst-0.4.2.dist-info/METADATA
amherst-0.4.2.dist-info/RECORD
