Metadata-Version: 2.3
Name: amherst
Version: 0.4.2
Summary: Add your description here
Author: Paw
Author-email: Paw <amherst+pawrequest@users.noreply.github.com>
Requires-Dist: pycommence
Requires-Dist: shipaw>=0.3.1
Requires-Dist: flaskwebgui>=1.2.2
Requires-Dist: pawdf
Requires-Dist: suppawt
Requires-Dist: pawlogger
Requires-Dist: pytest-asyncio>=1.2.0
Requires-Dist: hatchling>=1.27.0
Requires-Dist: python-multipart>=0.0.20
Requires-Dist: matplotlib>=3.10.6
Requires-Dist: pydantic-settings>=2.11.0
Requires-Dist: pydantic[email]>=2.11.9
Requires-Dist: fastapi>=0.117.1
Requires-Dist: docxtpl>=0.20.1
Requires-Dist: jinja2>=3.1.6
Requires-Dist: pandas>=2.3.3
Requires-Dist: loguru>=0.7.3
Requires-Dist: pyperclip>=1.11.0
Requires-Dist: xlrd>=2.0.2
Requires-Python: >=3.13
